<?xml version="1.0" encoding="UTF-8"?><record_update table="sys_ux_page_property">
    <sys_ux_page_property action="DELETE">
        <choices/>
        <description>Show/Hide search component in workspace header</description>
        <name>ws_active_search</name>
        <page display_value="OEHRM Access Management">8156b8111b186c10506855361a4bcb64</page>
        <suffix/>
        <sys_class_name>sys_ux_page_property</sys_class_name>
        <sys_created_by>admin</sys_created_by>
        <sys_created_on>2020-11-04 14:46:13</sys_created_on>
        <sys_id>c156f0511b186c10506855361a4bcb02</sys_id>
        <sys_mod_count>0</sys_mod_count>
        <sys_name>ws_active_search</sys_name>
        <sys_package display_value="OEHRM Access Management" source="x_snc_oehrm_tio_ac">85875b331bdd1010506855361a4bcb0d</sys_package>
        <sys_policy/>
        <sys_scope display_value="OEHRM Access Management">85875b331bdd1010506855361a4bcb0d</sys_scope>
        <sys_update_name>sys_ux_page_property_c156f0511b186c10506855361a4bcb02</sys_update_name>
        <sys_updated_by>admin</sys_updated_by>
        <sys_updated_on>2020-11-04 14:46:13</sys_updated_on>
        <type>boolean</type>
        <unique_name>x_snc_oehrm_tio_ac.ws_active_search</unique_name>
        <value>true</value>
    </sys_ux_page_property>
    <sys_translated_text action="DELETE" query="documentkey=c156f0511b186c10506855361a4bcb02"/>
    <sys_update_version action="INSERT_OR_UPDATE">
        <action>DELETE</action>
        <application display_value="OEHRM Access Management">85875b331bdd1010506855361a4bcb0d</application>
        <file_path/>
        <instance_id>706e2d97db40d0147527d7c8f4961929</instance_id>
        <instance_name>vademoinstance321demo</instance_name>
        <name>sys_ux_page_property_c156f0511b186c10506855361a4bcb02</name>
        <payload><![CDATA[<?xml version="1.0" encoding="UTF-8"?><record_update table="sys_ux_page_property"><sys_ux_page_property action="INSERT_OR_UPDATE"><choices/><description>Show/Hide search component in workspace header</description><name>ws_active_search</name><page display_value="OEHRM Access Management">8156b8111b186c10506855361a4bcb64</page><suffix/><sys_class_name>sys_ux_page_property</sys_class_name><sys_created_by>admin</sys_created_by><sys_created_on>2020-11-04 14:46:13</sys_created_on><sys_id>c156f0511b186c10506855361a4bcb02</sys_id><sys_mod_count>0</sys_mod_count><sys_name>ws_active_search</sys_name><sys_package display_value="OEHRM Access Management" source="x_snc_oehrm_tio_ac">85875b331bdd1010506855361a4bcb0d</sys_package><sys_policy/><sys_scope display_value="OEHRM Access Management">85875b331bdd1010506855361a4bcb0d</sys_scope><sys_update_name>sys_ux_page_property_c156f0511b186c10506855361a4bcb02</sys_update_name><sys_updated_by>admin</sys_updated_by><sys_updated_on>2020-11-04 14:46:13</sys_updated_on><type>boolean</type><unique_name>x_snc_oehrm_tio_ac.ws_active_search</unique_name><value>true</value></sys_ux_page_property><sys_translated_text action="delete_multiple" query="documentkey=c156f0511b186c10506855361a4bcb02"/></record_update>]]></payload>
        <payload_hash>859570070</payload_hash>
        <record_name>ws_active_search</record_name>
        <reverted_from/>
        <source>4f6a0f1f1bded050506855361a4bcb35</source>
        <source_table>sys_update_set</source_table>
        <state>previous</state>
        <sys_created_by>admin</sys_created_by>
        <sys_created_on>2020-11-04 14:46:13</sys_created_on>
        <sys_id>8956f0511b186c10506855361a4bcb03</sys_id>
        <sys_mod_count>0</sys_mod_count>
        <sys_recorded_at>17593b8f6be0000001</sys_recorded_at>
        <sys_updated_by>admin</sys_updated_by>
        <sys_updated_on>2020-11-04 14:46:13</sys_updated_on>
        <type>UX Page Property</type>
        <update_guid>8156f0513b186c10826680f07a2e6803</update_guid>
        <update_guid_history>8156f0513b186c10826680f07a2e6803:859570070</update_guid_history>
    </sys_update_version>
    <sys_metadata_delete action="INSERT_OR_UPDATE">
        <sys_audit_delete/>
        <sys_class_name>sys_metadata_delete</sys_class_name>
        <sys_created_by>admin</sys_created_by>
        <sys_created_on>2020-11-04 14:46:25</sys_created_on>
        <sys_db_object display_value="" name="sys_ux_page_property">sys_ux_page_property</sys_db_object>
        <sys_id>05d8270b726544b0802aa8510ae1b3c4</sys_id>
        <sys_metadata>c156f0511b186c10506855361a4bcb02</sys_metadata>
        <sys_mod_count>0</sys_mod_count>
        <sys_name>ws_active_search</sys_name>
        <sys_package display_value="OEHRM Access Management" source="x_snc_oehrm_tio_ac">85875b331bdd1010506855361a4bcb0d</sys_package>
        <sys_parent/>
        <sys_policy/>
        <sys_scope display_value="OEHRM Access Management">85875b331bdd1010506855361a4bcb0d</sys_scope>
        <sys_scope_delete display_value="">89e26e085493465cb1cd18725d68e710</sys_scope_delete>
        <sys_update_name>sys_ux_page_property_c156f0511b186c10506855361a4bcb02</sys_update_name>
        <sys_update_version display_value="sys_ux_page_property_c156f0511b186c10506855361a4bcb02">8956f0511b186c10506855361a4bcb03</sys_update_version>
        <sys_updated_by>admin</sys_updated_by>
        <sys_updated_on>2020-11-04 14:46:25</sys_updated_on>
    </sys_metadata_delete>
</record_update>
